tapwire/__init__.py
tapwire-1.1.dist-info/licenses/LICENSE
tapwire-1.1.dist-info/METADATA
tapwire-1.1.dist-info/WHEEL
tapwire-1.1.dist-info/top_level.txt
tapwire-1.1.dist-info/RECORD
