Metadata-Version: 2.4
Name: tapwire
Version: 1.1
Summary: A simple program for stealing variables from other programs. think of it like config files but python.
Author-email: StrawberryMilcRivers <chocomilccy@gmail.com>
License-Expression: MIT
Requires-Python: >=3.8
License-File: LICENSE
Dynamic: license-file
